{"mGNEHwsLJBQp8JOytcPIAw==":"mbr-1920x1280.jpg","9uNnEhyuMUEr3sn3uHFU4A==":"mbr-1920x1120.jpg","Q3KAzMvpOkhlRHbr5hUuzQ==":"mbr-1-1920x1280.jpg","9I1HDM++2pyX/h9bA7N5Rw==":"mbr-2-1920x1280.jpg","FqDynJq9oR3D+62IU7cvzQ==":"mbr-1920x1047.jpg","Ag74co3eKDSdGHyBYPXfnw==":"mbr-3-1920x1280.jpg","1YsgMyZ4vPxqsQHruacZvA==":"mbr-1920x1281.jpg","zMFMgVlOp3dP9UbHe4PlFA==":"mbr-4-1920x1280.jpg","hniVaZw8buHbaG0D23wzqg==":"images-128x128.png","xgf3sxJWBfnWDCPtH07y3A==":"lo-128x128.png","Pl3TsN1J344zcREmTPTlxg==":"lo2-128x128.png","d7imhLzVsKHJalpi9wvSJw==":"logo-128x128.png","2GUZh3dW9XQNsEO+gJwwtA==":"logo02-128x128.png","aFPjGulLkDGbqXqDA356ZQ==":"logo3-226x128.png","b1cYlq436OcKLhXxyw577w==":"mbr-5-1920x1280.jpg"}